{
  "team": "RWDM Brussels",
  "teamId": "rwdm",
  "season": "2023-24",
  "year": 2023,
  "players": [
    {"id":"theo-defourny-23","name":"Théo Defourny","position":"GK","nationality":"BEL","age":31,"appearances":22,"goals":0,"assists":0,"marketValue":550000,"internationalCaps":0,"awards":[],"overall":65},
    {"id":"guillaume-hubert-23","name":"Guillaume Hubert","position":"GK","nationality":"BEL","age":29,"appearances":8,"goals":0,"assists":0,"marketValue":400000,"internationalCaps":0,"awards":[],"overall":62},
    {"id":"luis-segovia-23","name":"Luis Segovia","position":"CB","nationality":"ECU","age":25,"appearances":22,"goals":0,"assists":0,"marketValue":1500000,"internationalCaps":5,"awards":[],"overall":65},
    {"id":"florian-le-joncour-23","name":"Florian Le Joncour","position":"CB","nationality":"FRA","age":28,"appearances":24,"goals":1,"assists":0,"marketValue":600000,"internationalCaps":0,"awards":[],"overall":64},
    {"id":"mamadou-sarr-23","name":"Mamadou Sarr","position":"CB","nationality":"SEN","age":18,"appearances":18,"goals":0,"assists":0,"marketValue":1000000,"internationalCaps":0,"awards":[],"overall":63},
    {"id":"youssouf-kone-23","name":"Youssouf Koné","position":"LB","alternativePositions":["LM"],"nationality":"MLI","age":27,"appearances":22,"goals":0,"assists":1,"marketValue":800000,"internationalCaps":25,"awards":[],"overall":64},
    {"id":"zakaria-el-ouahdi-23","name":"Zakaria El Ouahdi","position":"RB","alternativePositions":["RM"],"nationality":"MAR","age":21,"appearances":26,"goals":1,"assists":3,"marketValue":4500000,"internationalCaps":0,"awards":[],"overall":70},
    {"id":"pierre-dwomoh-23","name":"Pierre Dwomoh","position":"CM","alternativePositions":["CDM"],"nationality":"BEL","age":19,"appearances":24,"goals":2,"assists":3,"marketValue":2500000,"internationalCaps":0,"awards":[],"overall":68},
    {"id":"alexis-de-sart-23","name":"Alexis De Sart","position":"CM","alternativePositions":["CDM"],"nationality":"BEL","age":26,"appearances":24,"goals":1,"assists":2,"marketValue":700000,"internationalCaps":0,"awards":[],"overall":64},
    {"id":"jeff-reine-adelaide-23","name":"Jeff Reine-Adélaïde","position":"CAM","alternativePositions":["CM"],"nationality":"FRA","age":25,"appearances":16,"goals":2,"assists":3,"marketValue":2000000,"internationalCaps":0,"awards":[],"overall":68},
    {"id":"kylian-hazard-23","name":"Kylian Hazard","position":"LW","alternativePositions":["CAM"],"nationality":"BEL","age":27,"appearances":22,"goals":3,"assists":3,"marketValue":600000,"internationalCaps":0,"awards":[],"overall":64},
    {"id":"mickael-biron-23","name":"Mickaël Biron","position":"ST","nationality":"FRA","age":25,"appearances":28,"goals":9,"assists":2,"marketValue":2500000,"internationalCaps":0,"awards":[],"overall":70},
    {"id":"makhtar-gueye-23","name":"Makhtar Gueye","position":"ST","alternativePositions":["LW"],"nationality":"SEN","age":25,"appearances":20,"goals":5,"assists":2,"marketValue":2000000,"internationalCaps":5,"awards":[],"overall":67}
  ]
}
